LabExT/ExperimentManager.py
LabExT/Main.py
LabExT/PluginLoader.py
LabExT/Utils.py
LabExT/__init__.py
LabExT/__main__.py
LabExT/icon.png
LabExT/DocumentationEngine/Engine.py
LabExT/DocumentationEngine/MarkdownCleaner.py
LabExT/DocumentationEngine/__init__.py
LabExT/DocumentationEngine/mkdocs_files/mkdocs.yml
LabExT/DocumentationEngine/mkdocs_files/docs/index.md
LabExT/Experiments/AutosaveDict.py
LabExT/Experiments/StandardExperiment.py
LabExT/Experiments/ToDo.py
LabExT/Experiments/TypeHints.py
LabExT/Experiments/__init__.py
LabExT/Exporter/ExportAPI.py
LabExT/Exporter/ExportStep.py
LabExT/Exporter/ExportWizard.py
LabExT/Exporter/Formats/ExportCSV.py
LabExT/Exporter/Formats/ExportHDF5.py
LabExT/Exporter/Formats/__init__.py
LabExT/Instruments/DummyInstrument.py
LabExT/Instruments/LaserMainframeKeysight.py
LabExT/Instruments/LaserSimulator.py
LabExT/Instruments/OpticalSpectrumAnalyzerAQ6370C.py
LabExT/Instruments/OpticalSpectrumAnalyzerSimulator.py
LabExT/Instruments/PowerMeterGenericKeysight.py
LabExT/Instruments/PowerMeterN7744A.py
LabExT/Instruments/PowerMeterSimulator.py
LabExT/Instruments/ReusingResourceManager.py
LabExT/Instruments/__init__.py
LabExT/Instruments/instruments.config.default
LabExT/Instruments/InstrumentAPI/InstrumentAPI.py
LabExT/Instruments/InstrumentAPI/InstrumentSetup.py
LabExT/Instruments/InstrumentAPI/_Instrument.py
LabExT/Instruments/InstrumentAPI/__init__.py
LabExT/Logs/.gitignore
LabExT/Logs/CustomLogFormatter.py
LabExT/Logs/LoggingWidgetHandler.py
LabExT/Logs/MaxLevelFilter.py
LabExT/Logs/__init__.py
LabExT/Measurements/DummyMeas.py
LabExT/Measurements/InsertionLossSweep.py
LabExT/Measurements/ReadOSA.py
LabExT/Measurements/__init__.py
LabExT/Measurements/MeasAPI/Measparam.py
LabExT/Measurements/MeasAPI/Measurement.py
LabExT/Measurements/MeasAPI/README.md
LabExT/Measurements/MeasAPI/__init__.py
LabExT/Model/ExperimentHandler.py
LabExT/Model/WizardQuitException.py
LabExT/Model/__init__.py
LabExT/Model/Extensions/KillableThread.py
LabExT_pkg-2.3.1.dist-info/AUTHORS.md
LabExT_pkg-2.3.1.dist-info/LICENSE
LabExT_pkg-2.3.1.dist-info/METADATA
LabExT_pkg-2.3.1.dist-info/WHEEL
LabExT_pkg-2.3.1.dist-info/entry_points.txt
LabExT_pkg-2.3.1.dist-info/top_level.txt
LabExT_pkg-2.3.1.dist-info/RECORD
