Metadata-Version: 2.1
Name: LabExT_pkg
Version: 2.3.1
Summary: LabExT is a software environment for performing laboratory experiments on silicon-photonic devices.
Home-page: https://github.com/labext/LabExT
Author: Institute of Electromagnetic Fields (IEF) at ETH Zurich
Author-email: ief@ief.ee.ethz.ch
Maintainer: Marco Eppenberger
Maintainer-email: mail@mebg.ch
Project-URL: Documentation, https://labext.readthedocs.io
Classifier: Development Status :: 5 - Production/Stable
Classifier: Intended Audience :: Science/Research
Classifier: Programming Language :: Python :: 3.9
Classifier: Programming Language :: Python :: 3.10
Classifier: License :: OSI Approved :: GNU General Public License v3 (GPLv3)
Classifier: Operating System :: OS Independent
License-File: LICENSE
License-File: AUTHORS.md
Requires-Dist: babel ==2.15.0
Requires-Dist: bidict ==0.23.1
Requires-Dist: certifi ==2024.6.2
Requires-Dist: charset-normalizer ==3.3.2
Requires-Dist: click ==8.1.7
Requires-Dist: collision ==1.2.2
Requires-Dist: colorama ==0.4.6
Requires-Dist: contourpy ==1.2.1
Requires-Dist: cycler ==0.12.1
Requires-Dist: fonttools ==4.53.0
Requires-Dist: ghp-import ==2.1.0
Requires-Dist: griffe ==0.45.2
Requires-Dist: h5py ==3.11.0
Requires-Dist: idna ==3.7
Requires-Dist: importlib-metadata ==7.1.0
Requires-Dist: importlib-resources ==6.4.0
Requires-Dist: jinja2 ==3.1.4
Requires-Dist: kiwisolver ==1.4.5
Requires-Dist: markdown ==3.6
Requires-Dist: markupsafe ==2.1.5
Requires-Dist: matplotlib ==3.9.0
Requires-Dist: mergedeep ==1.3.4
Requires-Dist: mkdocs ==1.6.0
Requires-Dist: mkdocs-autorefs ==1.0.1
Requires-Dist: mkdocs-get-deps ==0.2.0
Requires-Dist: mkdocs-material ==9.5.26
Requires-Dist: mkdocs-material-extensions ==1.3.1
Requires-Dist: mkdocstrings ==0.25.1
Requires-Dist: mkdocstrings-python ==1.10.3
Requires-Dist: numpy ==1.26.4
Requires-Dist: packaging ==24.0
Requires-Dist: paginate ==0.5.6
Requires-Dist: pandas ==2.2.2
Requires-Dist: pathspec ==0.12.1
Requires-Dist: pillow ==10.3.0
Requires-Dist: platformdirs ==4.2.2
Requires-Dist: pygments ==2.18.0
Requires-Dist: pymdown-extensions ==10.8.1
Requires-Dist: pyparsing ==3.1.2
Requires-Dist: pyserial ==3.5
Requires-Dist: python-dateutil ==2.9.0.post0
Requires-Dist: pytz ==2024.1
Requires-Dist: pyusb ==1.2.1
Requires-Dist: pyvisa ==1.14.1
Requires-Dist: pyvisa-py ==0.7.2
Requires-Dist: pyyaml ==6.0.1
Requires-Dist: pyyaml-env-tag ==0.1
Requires-Dist: regex ==2024.5.15
Requires-Dist: requests ==2.32.3
Requires-Dist: scipy ==1.13.1
Requires-Dist: six ==1.16.0
Requires-Dist: tkinter-tooltip ==3.1.0
Requires-Dist: ttkwidgets ==0.13.0
Requires-Dist: typing-extensions ==4.12.2
Requires-Dist: tzdata ==2024.1
Requires-Dist: urllib3 ==2.2.1
Requires-Dist: watchdog ==4.0.1
Requires-Dist: zipp ==3.19.2
